variant_spark-0.5.5.data/data/share/variant-spark/data/CNAE-9-labels.csv
variant_spark-0.5.5.data/data/share/variant-spark/data/CNAE-9-wide.csv
variant_spark-0.5.5.data/data/share/variant-spark/data/CNAE-9.csv
variant_spark-0.5.5.data/data/share/variant-spark/data/README.md
variant_spark-0.5.5.data/data/share/variant-spark/data/ch22-model.ser
variant_spark-0.5.5.data/data/share/variant-spark/data/chr22-labels-hail.csv
variant_spark-0.5.5.data/data/share/variant-spark/data/chr22-labels.csv
variant_spark-0.5.5.data/data/share/variant-spark/data/chr22_1000.csv
variant_spark-0.5.5.data/data/share/variant-spark/data/chr22_1000.vcf
variant_spark-0.5.5.data/data/share/variant-spark/data/chr22_1000.vcf.bgz
variant_spark-0.5.5.data/data/share/variant-spark/data/chr22_1000.vcf.bz2
variant_spark-0.5.5.data/data/share/variant-spark/data/chr22_1000.vcf.gz
variant_spark-0.5.5.data/data/share/variant-spark/data/chr22_1000_GRCh38.vcf
variant_spark-0.5.5.data/data/share/variant-spark/data/chr22_1000_full_pheno.csv
variant_spark-0.5.5.data/data/share/variant-spark/data/chr22_1000_missing.vcf
variant_spark-0.5.5.data/data/share/variant-spark/data/chr22_1000_pheno-wide.csv
variant_spark-0.5.5.data/data/share/variant-spark/data/chr22_1000_pheno.csv
variant_spark-0.5.5.data/data/share/variant-spark/data/har_aal.csv.bz2
variant_spark-0.5.5.data/data/share/variant-spark/data/har_aal_labels.csv
variant_spark-0.5.5.data/data/share/variant-spark/data/importance-chr22-HG00097.csv
variant_spark-0.5.5.data/data/share/variant-spark/data/ranger-labels_10000.csv
variant_spark-0.5.5.data/data/share/variant-spark/data/ranger-types.csv
variant_spark-0.5.5.data/data/share/variant-spark/data/ranger-wide_1000_10000.csv.bz2
variant_spark-0.5.5.data/scripts/find-varspark-jar
variant_spark-0.5.5.data/scripts/jvariant-spark
variant_spark-0.5.5.data/scripts/variant-spark
varspark/__init__.py
varspark/cli.py
varspark/core.py
varspark/etc.py
varspark/java.py
varspark/lang.py
varspark/utils.py
variant_spark-0.5.5.dist-info/LICENSE.txt
variant_spark-0.5.5.dist-info/METADATA
variant_spark-0.5.5.dist-info/WHEEL
variant_spark-0.5.5.dist-info/entry_points.txt
variant_spark-0.5.5.dist-info/top_level.txt
variant_spark-0.5.5.dist-info/RECORD
